pinmix/__init__.py
pinmix/cmdline.py
pinmix/filler.py
pinmix/opendoc_factory.py
pinmix-0.2.dist-info/DESCRIPTION.rst
pinmix-0.2.dist-info/METADATA
pinmix-0.2.dist-info/RECORD
pinmix-0.2.dist-info/WHEEL
pinmix-0.2.dist-info/entry_points.txt
pinmix-0.2.dist-info/metadata.json
pinmix-0.2.dist-info/top_level.txt
