Metadata-Version: 2.0
Name: pinmix
Version: 0.2
Summary: UNKNOWN
Home-page: UNKNOWN
Author: UNKNOWN
Author-email: UNKNOWN
License: UNKNOWN
Platform: UNKNOWN
Requires-Dist: jieba
Requires-Dist: odfpy
Requires-Dist: xpinyin (==0.5.5)
